brynq_sdk_sage_100_france/__init__.py
brynq_sdk_sage_100_france/absence.py
brynq_sdk_sage_100_france/address.py
brynq_sdk_sage_100_france/bank_info.py
brynq_sdk_sage_100_france/company.py
brynq_sdk_sage_100_france/contract.py
brynq_sdk_sage_100_france/department.py
brynq_sdk_sage_100_france/employee.py
brynq_sdk_sage_100_france/employee_insurance.py
brynq_sdk_sage_100_france/event.py
brynq_sdk_sage_100_france/family.py
brynq_sdk_sage_100_france/insurance.py
brynq_sdk_sage_100_france/leave.py
brynq_sdk_sage_100_france/position.py
brynq_sdk_sage_100_france/sage_100_france.py
brynq_sdk_sage_100_france/salary.py
brynq_sdk_sage_100_france/service.py
brynq_sdk_sage_100_france/test_excel_import.py
brynq_sdk_sage_100_france/work.py
brynq_sdk_sage_100_france/schemas/__init__.py
brynq_sdk_sage_100_france/schemas/absence.py
brynq_sdk_sage_100_france/schemas/address.py
brynq_sdk_sage_100_france/schemas/bank_info.py
brynq_sdk_sage_100_france/schemas/company.py
brynq_sdk_sage_100_france/schemas/contract.py
brynq_sdk_sage_100_france/schemas/department.py
brynq_sdk_sage_100_france/schemas/employee.py
brynq_sdk_sage_100_france/schemas/employee_insurance.py
brynq_sdk_sage_100_france/schemas/event.py
brynq_sdk_sage_100_france/schemas/family.py
brynq_sdk_sage_100_france/schemas/insurance.py
brynq_sdk_sage_100_france/schemas/leave.py
brynq_sdk_sage_100_france/schemas/position.py
brynq_sdk_sage_100_france/schemas/salary.py
brynq_sdk_sage_100_france/schemas/service.py
brynq_sdk_sage_100_france/schemas/work.py
brynq_sdk_sage_100_france-1.2.1.dist-info/METADATA
brynq_sdk_sage_100_france-1.2.1.dist-info/WHEEL
brynq_sdk_sage_100_france-1.2.1.dist-info/top_level.txt
brynq_sdk_sage_100_france-1.2.1.dist-info/RECORD
