Metadata-Version: 2.4
Name: brynq_sdk_sage_100_france
Version: 1.2.1
Summary: Sage 100 France wrapper from BrynQ
Author: BrynQ
Author-email: support@brynq.com
License: BrynQ License
Requires-Dist: brynq-sdk-brynq<5,>=4
Dynamic: author
Dynamic: author-email
Dynamic: description
Dynamic: license
Dynamic: requires-dist
Dynamic: summary
